notary/__init__.py
notary/__main__.py
notary/__version__.py
notary/cli.py
notary/models.py
notary/utils.py
notary/licenses/agpl-3.0.md
notary/licenses/apache-2.0.md
notary/licenses/gpl-3.0.md
notary/licenses/lgpl-3.0.md
notary/licenses/mit.md
notary/licenses/mpl-2.0.md
notary/licenses/unlicense.md
notary-0.1.17.dist-info/DESCRIPTION.rst
notary-0.1.17.dist-info/METADATA
notary-0.1.17.dist-info/RECORD
notary-0.1.17.dist-info/WHEEL
notary-0.1.17.dist-info/entry_points.txt
notary-0.1.17.dist-info/metadata.json
notary-0.1.17.dist-info/top_level.txt
