Metadata-Version: 2.0
Name: notary
Version: 0.1.17
Summary: License your project
Home-page: https://github.com/sxn/notary
Author: Sorin Muntean
Author-email: contact@sorinmuntean.ro
License: MIT
Platform: UNKNOWN
Classifier: Programming Language :: Python :: 3.6
Requires-Dist: click
Requires-Dist: crayons
